rab_the_bit/__init__.py
rab_the_bit/__version__.py
rab_the_bit/rab_the_bit.py
rab_the_bit-0.0.93.dist-info/LICENSE
rab_the_bit-0.0.93.dist-info/METADATA
rab_the_bit-0.0.93.dist-info/WHEEL
rab_the_bit-0.0.93.dist-info/entry_points.txt
rab_the_bit-0.0.93.dist-info/RECORD
