Metadata-Version: 2.1
Name: rab_the_bit
Version: 0.0.93
Summary: A wrapper around Kombu to use RabbitMQ, specialy on docker images
Home-page: https://github.com/vliz-be-opsci/py-rabbit
License: MIT
Author: Vlaams Instituut voor de Zee (VLIZ), João Santos
Author-email: jotaflame@gmail.com
Requires-Python: >=3.8.1,<4.0.0
Classifier: License :: OSI Approved :: MIT License
Classifier: Programming Language :: Python
Classifier: Programming Language :: Python :: 3
Classifier: Programming Language :: Python :: 3.9
Classifier: Programming Language :: Python :: 3.10
Classifier: Programming Language :: Python :: 3.11
Classifier: Programming Language :: Python :: 3.12
Classifier: Programming Language :: Python :: 3.8
Requires-Dist: kombu
Project-URL: Repository, https://github.com/vliz-be-opsci/py-rabbit
